{
    "Nike SB Dunk Low Pro - White/Met.Gold-Phy Blue": {
        "image": "http://supplystore.com.au/images/items/DC9936-100/1.jpg",
        "link": "https://www.supplystore.com.au/brands/nike-sb-dunk-low-pro-whitemet.gold-phy-blue/c-28/p-236946",
        "sizes": {
            "10": "10 [Sold Out]",
            "10.5": "10.5 [Sold Out]",
            "11": "11 [Sold Out]",
            "11.5": "11.5 [Sold Out]",
            "12": "12 [Sold Out]",
            "12.5": "12.5 [Sold Out]",
            "13": "13 [Sold Out]",
            "4": "4 [Sold Out]",
            "4.5": "4.5 [Sold Out]",
            "5": "5 [Sold Out]",
            "5.5": "5.5 [Sold Out]",
            "6": "6 [Sold Out]",
            "6.5": "6.5 [Sold Out]",
            "7": "7 [Sold Out]",
            "7.5": "7.5 [Sold Out]",
            "8": "8 [Sold Out]",
            "8.5": "8.5 [Sold Out]",
            "9": "9 [Sold Out]",
            "9.5": "9.5 [Sold Out]"
        }
    },
    "W' Nike Dunk Low SP - College Navy/Wolf Grey": {
        "image": "http://supplystore.com.au/images/items/DD1768-400/1.jpg",
        "link": "https://www.supplystore.com.au/brands/w%27-nike-dunk-low-sp-college-navywolf-grey/c-28/p-237636",
        "sizes": {
            "10": "10 [Sold Out]",
            "10.5": "10.5 [Sold Out]",
            "11": "11 [Sold Out]",
            "7": "7 [Sold Out]",
            "7.5": "7.5 [Sold Out]",
            "8": "8 [Sold Out]",
            "8.5": "8.5 [Sold Out]",
            "9": "9 [Sold Out]",
            "9.5": "9.5 [Sold Out]"
        }
    }
}